adsl/__init__.py
adsl/adslconnector.py
adslconnector-0.0.3.dist-info/LICENSE
adslconnector-0.0.3.dist-info/METADATA
adslconnector-0.0.3.dist-info/WHEEL
adslconnector-0.0.3.dist-info/top_level.txt
adslconnector-0.0.3.dist-info/RECORD
