Metadata-Version: 2.1
Name: adslconnector
Version: 0.0.3
Summary: Adsl Connector
Home-page: https://github.com/pypa/sampleproject
Author: wengo
Author-email: 398711943@qq.com
License: UNKNOWN
Platform: UNKNOWN
Classifier: Programming Language :: Python :: 3
Classifier: License :: OSI Approved :: MIT License
Classifier: Operating System :: OS Independent
Requires-Python: >=3.6
